forexconnect/EachRowListener.py
forexconnect/ForexConnect.py
forexconnect/LiveHistory.py
forexconnect/ResponseListener.py
forexconnect/SessionStatusListener.py
forexconnect/TableListener.py
forexconnect/TableManagerListener.py
forexconnect/__init__.py
forexconnect/common.py
forexconnect/errors.py
forexconnect/lib/__init__.py
forexconnect/lib/fxcorepy.so
forexconnect/lib/libForexConnect.so
forexconnect/lib/libboost_python3.so.1.64.0
forexconnect/lib/libboost_system.so.1.64.0
forexconnect/lib/libfxmsg.so
forexconnect/lib/libfxtp.so
forexconnect/lib/libgsexpat.so
forexconnect/lib/libgstool3.so
forexconnect/lib/libhttplib.so
forexconnect/lib/liblog4cplus.so
forexconnect/lib/liblogger.so
forexconnect/lib/libpdas.so
forexconnect/lib/libpricehistorymgr.so.2.8.0
forexconnect/lib/libpython3.7m.so
forexconnect/lib/libquotesmgr2.so.2.8
forexconnect/lib/libsqlite3.8.so
forexconnect/lib/requirements.txt
forexconnect/lib/__pycache__/__init__.cpython-310.pyc
monedadigitalf-1.6.43.post3.dist-info/METADATA
monedadigitalf-1.6.43.post3.dist-info/WHEEL
monedadigitalf-1.6.43.post3.dist-info/top_level.txt
monedadigitalf-1.6.43.post3.dist-info/RECORD
